[
    {
        "Floor Code": "01",
        "Room Code": "1096A",
        "Description": "Shaft Space",
        "Department Name": "Shaft Spaces"
    },
    {
        "Floor Code": "01",
        "Room Code": "1437",
        "Description": "Mechanical",
        "Department Name": "A&F Maintenance & Operations"
    },
    {
        "Floor Code": "01",
        "Room Code": "1442D",
        "Description": "Mechanical",
        "Department Name": "A&F Maintenance & Operations"
    },
    {
        "Floor Code": "01",
        "Room Code": "1505",
        "Description": "Reception/Waiting",
        "Department Name": "SA Testing Services"
    },
    {
        "Floor Code": "01",
        "Room Code": "1510",
        "Description": "Internal Office Circ",
        "Department Name": "SA Testing Services"
    },
    {
        "Floor Code": "01",
        "Room Code": "1510A",
        "Description": "Office",
        "Department Name": "SA Testing Services"
    },
    {
        "Floor Code": "01",
        "Room Code": "1510B",
        "Description": "Conference",
        "Department Name": "SA Testing Services"
    },
    {
        "Floor Code": "01",
        "Room Code": "1510C",
        "Description": "Modular",
        "Department Name": "SA Testing Services"
    },
    {
        "Floor Code": "01",
        "Room Code": "1510D",
        "Description": "Office",
        "Department Name": "SA Testing Services"
    },
    {
        "Floor Code": "01",
        "Room Code": "1510E",
        "Description": "Office",
        "Department Name": "SA Testing Services"
    },
    {
        "Floor Code": "01",
        "Room Code": "1510F",
        "Description": "Reception/Waiting",
        "Department Name": "SA Testing Services"
    },
    {
        "Floor Code": "01",
        "Room Code": "1510G",
        "Description": "Counseling/Testing",
        "Department Name": "SA Testing Services"
    },
    {
        "Floor Code": "01",
        "Room Code": "1510H",
        "Description": "Telecommunications Room",
        "Department Name": "DTS Enterprise Infrastructure Tech Serv"
    },
    {
        "Floor Code": "01",
        "Room Code": "1510J",
        "Description": "Telecommunications Room",
        "Department Name": "DTS Enterprise Infrastructure Tech Serv"
    },
    {
        "Floor Code": "01",
        "Room Code": "1510K",
        "Description": "Counseling/Testing",
        "Department Name": "SA Testing Services"
    },
    {
        "Floor Code": "01",
        "Room Code": "1519",
        "Description": "Custodial",
        "Department Name": "A&F Building Services"
    },
    {
        "Floor Code": "01",
        "Room Code": "1520",
        "Description": "Restroom Female",
        "Department Name": "A&F Building Services"
    },
    {
        "Floor Code": "01",
        "Room Code": "1521",
        "Description": "Restroom Female",
        "Department Name": "A&F Building Services"
    },
    {
        "Floor Code": "01",
        "Room Code": "1522",
        "Description": "Restroom Male",
        "Department Name": "A&F Building Services"
    },
    {
        "Floor Code": "01",
        "Room Code": "1523",
        "Description": "Restroom Male",
        "Department Name": "A&F Building Services"
    },
    {
        "Floor Code": "01",
        "Room Code": "1601",
        "Description": "Mechanical",
        "Department Name": "A&F Maintenance & Operations"
    },
    {
        "Floor Code": "01",
        "Room Code": "1602",
        "Description": "Mechanical",
        "Department Name": "A&F Maintenance & Operations"
    },
    {
        "Floor Code": "01",
        "Room Code": "1605",
        "Description": "Office",
        "Department Name": "SA Testing Services"
    },
    {
        "Floor Code": "01",
        "Room Code": "1607",
        "Description": "Office",
        "Department Name": "SA Testing Services"
    },
    {
        "Floor Code": "01",
        "Room Code": "1609",
        "Description": "Counseling/Testing",
        "Department Name": "SA Testing Services"
    },
    {
        "Floor Code": "01",
        "Room Code": "1611",
        "Description": "Counseling/Testing",
        "Department Name": "SA Testing Services"
    },
    {
        "Floor Code": "01",
        "Room Code": "1612",
        "Description": "Break Room",
        "Department Name": "SA Testing Services"
    },
    {
        "Floor Code": "01",
        "Room Code": "1614",
        "Description": "Counseling/Testing",
        "Department Name": "SA Testing Services"
    },
    {
        "Floor Code": "01",
        "Room Code": "1615",
        "Description": "Counseling/Testing",
        "Department Name": "SA Testing Services"
    },
    {
        "Floor Code": "01",
        "Room Code": "1616",
        "Description": "Counseling/Testing",
        "Department Name": "SA Testing Services"
    },
    {
        "Floor Code": "01",
        "Room Code": "1619",
        "Description": "Counseling/Testing",
        "Department Name": "SA Testing Services"
    },
    {
        "Floor Code": "01",
        "Room Code": "1620",
        "Description": "Counseling/Testing",
        "Department Name": "SA Testing Services"
    },
    {
        "Floor Code": "01",
        "Room Code": "1621",
        "Description": "Counseling/Testing",
        "Department Name": "SA Testing Services"
    },
    {
        "Floor Code": "01",
        "Room Code": "1622",
        "Description": "Counseling/Testing",
        "Department Name": "SA Testing Services"
    },
    {
        "Floor Code": "01",
        "Room Code": "1623",
        "Description": "Counseling/Testing",
        "Department Name": "SA Testing Services"
    },
    {
        "Floor Code": "01",
        "Room Code": "1625",
        "Description": "Counseling/Testing",
        "Department Name": "SA Testing Services"
    },
    {
        "Floor Code": "01",
        "Room Code": "1626",
        "Description": "Counseling/Testing",
        "Department Name": "SA Testing Services"
    },
    {
        "Floor Code": "01",
        "Room Code": "1997A",
        "Description": "Elevator",
        "Department Name": "Shaft Spaces"
    },
    {
        "Floor Code": "01",
        "Room Code": "1998A",
        "Description": "Stair",
        "Department Name": "Hallways"
    },
    {
        "Floor Code": "01",
        "Room Code": "1998B",
        "Description": "Stair",
        "Department Name": "Hallways"
    },
    {
        "Floor Code": "01",
        "Room Code": "1998C",
        "Description": "Stair",
        "Department Name": "Hallways"
    },
    {
        "Floor Code": "01",
        "Room Code": "1999",
        "Description": "Corridor",
        "Department Name": "Hallways"
    }
]