[
    {
        "Floor Code": "01",
        "Room Code": "102",
        "Description": "Custodial",
        "Department Name": "A&F Building Services"
    },
    {
        "Floor Code": "01",
        "Room Code": "113",
        "Description": "Mechanical",
        "Department Name": "A&F Maintenance & Operations"
    },
    {
        "Floor Code": "01",
        "Room Code": "113A",
        "Description": "Mechanical",
        "Department Name": "A&F Maintenance & Operations"
    },
    {
        "Floor Code": "01",
        "Room Code": "150",
        "Description": "Other Lab Svc Instr",
        "Department Name": "CCM Keyboard Studies"
    },
    {
        "Floor Code": "01",
        "Room Code": "160",
        "Description": "Mechanical",
        "Department Name": "A&F Maintenance & Operations"
    },
    {
        "Floor Code": "01",
        "Room Code": "170",
        "Description": "Mechanical",
        "Department Name": "A&F Maintenance & Operations"
    },
    {
        "Floor Code": "01",
        "Room Code": "170A",
        "Description": "Mechanical",
        "Department Name": "A&F Maintenance & Operations"
    },
    {
        "Floor Code": "01",
        "Room Code": "180",
        "Description": "Performance Study Lab (Unsch)",
        "Department Name": "CCM Composition, Musicology & Theory"
    },
    {
        "Floor Code": "01",
        "Room Code": "182",
        "Description": "Performance Study Lab (Unsch)",
        "Department Name": "CCM Composition, Musicology & Theory"
    },
    {
        "Floor Code": "01",
        "Room Code": "184",
        "Description": "Restroom All Gender",
        "Department Name": "A&F Building Services"
    },
    {
        "Floor Code": "01",
        "Room Code": "186",
        "Description": "Custodial",
        "Department Name": "A&F Building Services"
    },
    {
        "Floor Code": "01",
        "Room Code": "189",
        "Description": "Mechanical",
        "Department Name": "A&F Maintenance & Operations"
    },
    {
        "Floor Code": "01",
        "Room Code": "197A",
        "Description": "Elevator",
        "Department Name": "Shaft Spaces"
    },
    {
        "Floor Code": "01",
        "Room Code": "197B",
        "Description": "Elevator",
        "Department Name": "Shaft Spaces"
    },
    {
        "Floor Code": "01",
        "Room Code": "197C",
        "Description": "Elevator",
        "Department Name": "Shaft Spaces"
    },
    {
        "Floor Code": "01",
        "Room Code": "198C",
        "Description": "Stair",
        "Department Name": "Hallways"
    },
    {
        "Floor Code": "01",
        "Room Code": "198D",
        "Description": "Stair",
        "Department Name": "Hallways"
    },
    {
        "Floor Code": "01",
        "Room Code": "198E",
        "Description": "Stair",
        "Department Name": "Hallways"
    },
    {
        "Floor Code": "01",
        "Room Code": "199",
        "Description": "Corridor",
        "Department Name": "Hallways"
    }
]